{
    "fluentMethods": true,
    "relationships": [],
    "fields": [
        {
            "fieldName": "name",
            "fieldType": "String",
            "fieldValidateRules": [
                "required",
                "maxlength"
            ],
            "fieldValidateRulesMaxlength": 100
        },
        {
            "fieldName": "isDefault",
            "fieldType": "Boolean"
        },
        {
            "fieldName": "version",
            "fieldType": "CatalogVersion",
            "fieldValues": "ONLINE,STAGE",
            "fieldValidateRules": [
                "required"
            ]
        }
    ],
    "changelogDate": "20170414145811",
    "entityTableName": "catalog",
    "dto": "no",
    "pagination": "no",
    "service": "no"
}